setup.py
tests/testHelpers.py
tests/testVsMetaBase.py
tests/testVsMetaMovieEncoder.py
tests/testvsmetaDecoder.py
tests/testvsmetaSeriesEncoder.py
vsmetaCodec/__init__.py
vsmetaCodec/vsmetaBase.py
vsmetaCodec/vsmetaCode.py
vsmetaCodec/vsmetaDecoder.py
vsmetaCodec/vsmetaEncoder.py
vsmetaCodec/vsmetaInfo.py
vsmetaEncoder-1.1.1.dist-info/LICENSE
vsmetaEncoder-1.1.1.dist-info/METADATA
vsmetaEncoder-1.1.1.dist-info/WHEEL
vsmetaEncoder-1.1.1.dist-info/top_level.txt
vsmetaEncoder-1.1.1.dist-info/RECORD
