Metadata-Version: 2.1
Name: vsmetaEncoder
Version: 1.1.1
Summary: A module to encode and decode media information with Synology's vsmeta file format.
Author-email: Thomas Meder <tom@tommho.net>, Bernd Frey <bfy@online.de>
Project-URL: Homepage, https://github.com/Berfre/vsMetaFileCodec
Project-URL: Issues, https://github.com/Berfre/vsMetaFileCodec/issues
Classifier: Programming Language :: Python :: 3
Classifier: License :: OSI Approved :: MIT License
Classifier: Operating System :: OS Independent
Classifier: Topic :: System :: Logging
Requires-Python: >=3.8
License-File: LICENSE
